es7s/__init__.py
es7s/_import.py
es7s/_version.py
es7s/cli/.stub.py_
es7s/cli/.stub.sh_
es7s/cli/__init__.py
es7s/cli/__main__.py
es7s/cli/_base.py
es7s/cli/_base_opts_params.py
es7s/cli/_decorators.py
es7s/cli/_entrypoint.py
es7s/cli/_foreign.py
es7s/cli/_logo.py
es7s/cli/_template.py
es7s/cli/autoaction.py
es7s/cli/autodiscover.py
es7s/cli/config/__init__.py
es7s/cli/config/_base.py
es7s/cli/config/diff.py
es7s/cli/config/edit.py
es7s/cli/config/get.py
es7s/cli/config/list.py
es7s/cli/config/reset.py
es7s/cli/config/set.py
es7s/cli/exec_/__init__.py
es7s/cli/exec_/autoterm.py
es7s/cli/exec_/bdb.sh
es7s/cli/exec_/bulk-dload-sf.sh
es7s/cli/exec_/cal.py
es7s/cli/exec_/ccc.py
es7s/cli/exec_/chrome-nosec.sh
es7s/cli/exec_/columns.py
es7s/cli/exec_/connect_times.py
es7s/cli/exec_/describe.sh
es7s/cli/exec_/dss.sh
es7s/cli/exec_/edit_image.py
es7s/cli/exec_/esqdb.py
es7s/cli/exec_/faka2.sh
es7s/cli/exec_/fudrapp.py
es7s/cli/exec_/grobocop.py
es7s/cli/exec_/groboscope.py
es7s/cli/exec_/hilight_num.py
es7s/cli/exec_/kamon.sh
es7s/cli/exec_/keys.py
es7s/cli/exec_/lingvini.py
es7s/cli/exec_/ls.py
es7s/cli/exec_/net-inspect.sh
es7s/cli/exec_/notify.py
es7s/cli/exec_/open_terminal.py
es7s/cli/exec_/padbox.sh
es7s/cli/exec_/pet.py
es7s/cli/exec_/pgrek.sh
es7s/cli/exec_/pup.py
es7s/cli/exec_/render_emoji.py
es7s/cli/exec_/sendkey.sh
es7s/cli/exec_/shocks.sh
es7s/cli/exec_/sun.py
es7s/cli/exec_/sustain.sh
es7s/cli/exec_/switch_wspace.py
es7s/cli/exec_/sync_pub_defs.py
es7s/cli/exec_/time.py
es7s/cli/exec_/transmorph.py
es7s/cli/exec_/watson.sh
es7s/cli/exec_/watson2.sh
es7s/cli/exec_/word_combiner.py
es7s/cli/exec_/wrap.py
es7s/cli/exec_/xdotool.py
es7s/cli/exec_/xterm_svg_to_png.sh
es7s/cli/exec_/colors/__init__.py
es7s/cli/exec_/colors/hsv.py
es7s/cli/exec_/colors/legacy.sh
es7s/cli/exec_/colors/rgb.py
es7s/cli/exec_/fan/__init__.py
es7s/cli/exec_/fan/_template.ptpl
es7s/cli/exec_/fan/css-units.ptpl
es7s/cli/exec_/fan/entrypoint.py
es7s/cli/exec_/fan/git-revisions.ptpl
es7s-3.98.0.dev0.dist-info/METADATA
es7s-3.98.0.dev0.dist-info/WHEEL
es7s-3.98.0.dev0.dist-info/entry_points.txt
es7s-3.98.0.dev0.dist-info/RECORD
