Metadata-Version: 2.1
Name: es7s
Version: 3.98.0.dev0
Summary: es7s system (un-)installer, shared code, settings manager
Project-URL: Homepage, https://github.com/es7s/core
Author-email: Aleksandr Shavykin <0.delameter@gmail.com>
License: MIT
Keywords: cli,console,daemon,es7s,monitor,prmopt,shell,system,terminal
Classifier: Development Status :: 3 - Alpha
Classifier: Environment :: Console
Classifier: Environment :: No Input/Output (Daemon)
Classifier: Intended Audience :: Developers
Classifier: Intended Audience :: System Administrators
Classifier: License :: OSI Approved :: MIT License
Classifier: Operating System :: POSIX :: Linux
Classifier: Programming Language :: Python
Classifier: Programming Language :: Python :: 3
Classifier: Programming Language :: Python :: 3.10
Classifier: Topic :: Terminals
Requires-Python: >=3.10
Requires-Dist: beautifulsoup4~=4.12
Requires-Dist: click~=8.1
Requires-Dist: deprecated
Requires-Dist: emoji~=2.8
Requires-Dist: es7s-commons>=1.8.0
Requires-Dist: holms>=1.4.0
Requires-Dist: lxml~=4.9
Requires-Dist: pillow~=9.1
Requires-Dist: psutil~=5.9
Requires-Dist: pysuncalc>=0.0.1
Requires-Dist: pytermor>=2.118.0.dev0
Requires-Dist: python-daemon~=2.3
Requires-Dist: python-dateutil~=2.8
Requires-Dist: python-levenshtein~=0.21
Requires-Dist: pyyaml~=6.0
Requires-Dist: readchar~=4.0
Requires-Dist: requests[socks]~=2.28
Requires-Dist: werkzeug~=3.0.1
Provides-Extra: build
Requires-Dist: build~=1.0; extra == 'build'
Requires-Dist: setuptools~=65.3; extra == 'build'
Requires-Dist: twine~=4.0; extra == 'build'
Provides-Extra: dev
Requires-Dist: ipython==8.18.1; extra == 'dev'
Requires-Dist: line-profiler-pycharm~=1.1.0; extra == 'dev'
Requires-Dist: memory-profiler~=0.61.0; extra == 'dev'
Requires-Dist: memray~=1.9.1; extra == 'dev'
Requires-Dist: pydeps~=1.10; extra == 'dev'
Provides-Extra: gtk
Requires-Dist: pycairo~=1.23; extra == 'gtk'
Requires-Dist: pygobject~=3.42; extra == 'gtk'
Provides-Extra: test
Requires-Dist: coverage[toml]~=6.4; extra == 'test'
Requires-Dist: pytest-cov~=4.1; extra == 'test'
Requires-Dist: pytest~=7.1; extra == 'test'
Requires-Dist: ruff>=0.3.0; extra == 'test'
Provides-Extra: web
Requires-Dist: flask~=2.2.2; extra == 'web'
Requires-Dist: gunicorn~=20.1.0; extra == 'web'
